{
  "name": "add-section-rename",
  "input": "@add \"# Original Title\" from [file.md] as \"# New Title\"",
  "expected": "# New Title\nContent under this section",
  "directives": [
    "@add \"# Original Title\" from [file.md] as \"# New Title\""
  ],
  "ast": [
    {
      "type": "Directive",
      "nodeId": "44f3d250-6007-43af-9b56-4d34efbef7bb",
      "location": {
        "start": {
          "offset": 0,
          "line": 1,
          "column": 1
        },
        "end": {
          "offset": 55,
          "line": 1,
          "column": 56
        }
      },
      "kind": "add",
      "subtype": "addSection",
      "source": "section",
      "values": {
        "sectionTitle": [
          {
            "type": "Text",
            "nodeId": "20fb46c3-1d90-44c8-b824-ddab7f3b8e01",
            "location": {
              "start": {
                "offset": 5,
                "line": 1,
                "column": 6
              },
              "end": {
                "offset": 23,
                "line": 1,
                "column": 24
              }
            },
            "content": "# Original Title"
          }
        ],
        "path": [
          {
            "type": "Text",
            "nodeId": "f4a63f68-eb54-4338-8d23-8b493f0a0abe",
            "location": {
              "start": {
                "offset": 30,
                "line": 1,
                "column": 31
              },
              "end": {
                "offset": 37,
                "line": 1,
                "column": 38
              }
            },
            "content": "file.md"
          }
        ],
        "newTitle": [
          {
            "type": "Text",
            "nodeId": "df7d2c94-dc6d-4d66-a382-4dd720125372",
            "location": {
              "start": {
                "offset": 42,
                "line": 1,
                "column": 43
              },
              "end": {
                "offset": 55,
                "line": 1,
                "column": 56
              }
            },
            "content": "# New Title"
          }
        ]
      },
      "raw": {
        "sectionTitle": "# Original Title",
        "path": "file.md",
        "newTitle": "# New Title"
      },
      "meta": {
        "path": {
          "hasVariables": false,
          "isAbsolute": false,
          "hasExtension": true,
          "extension": "md"
        }
      }
    }
  ],
  "metadata": {
    "kind": "add",
    "subtype": "section",
    "variant": "rename"
  }
}