{
  "name": "import-selected",
  "input": "@import {greeting, count} from [utils.mld]\n@add @greeting\n@add @count",
  "expected": "Hello, world!\n42",
  "directives": [
    "@import {greeting, count} from [utils.mld]",
    "@add @greeting",
    "@add @count"
  ],
  "ast": [
    {
      "type": "Directive",
      "nodeId": "13e9a1ee-c407-44c4-b0a0-554982025ef8",
      "location": {
        "start": {
          "offset": 0,
          "line": 1,
          "column": 1
        },
        "end": {
          "offset": 42,
          "line": 1,
          "column": 43
        }
      },
      "kind": "import",
      "subtype": "importSelected",
      "source": "path",
      "values": {
        "imports": [
          {
            "type": "VariableReference",
            "nodeId": "5c3d12a9-3d92-4ea0-b660-1a1175b5ca68",
            "location": {
              "start": {
                "offset": 0,
                "line": 1,
                "column": 1
              },
              "end": {
                "offset": 0,
                "line": 1,
                "column": 1
              }
            },
            "valueType": "import",
            "isVariableReference": true,
            "identifier": "greeting",
            "alias": null
          },
          {
            "type": "VariableReference",
            "nodeId": "2c052784-044b-4d51-873c-e0fcb7df9c80",
            "location": {
              "start": {
                "offset": 0,
                "line": 1,
                "column": 1
              },
              "end": {
                "offset": 0,
                "line": 1,
                "column": 1
              }
            },
            "valueType": "import",
            "isVariableReference": true,
            "identifier": "count",
            "alias": null
          }
        ],
        "path": [
          {
            "type": "Text",
            "nodeId": "4d23698f-0d8c-49ac-8608-c8731af231a4",
            "location": {
              "start": {
                "offset": 32,
                "line": 1,
                "column": 33
              },
              "end": {
                "offset": 41,
                "line": 1,
                "column": 42
              }
            },
            "content": "utils.mld"
          }
        ]
      },
      "raw": {
        "imports": "greeting, count",
        "path": "utils.mld"
      },
      "meta": {
        "path": {
          "hasVariables": false,
          "isAbsolute": false,
          "hasExtension": true,
          "extension": "mld"
        }
      }
    },
    {
      "type": "Directive",
      "nodeId": "413ca181-9e0f-46f1-b500-10b726ceae05",
      "location": {
        "start": {
          "offset": 0,
          "line": 1,
          "column": 1
        },
        "end": {
          "offset": 14,
          "line": 1,
          "column": 15
        }
      },
      "kind": "add",
      "subtype": "addVariable",
      "source": "variable",
      "values": {
        "variable": [
          {
            "type": "VariableReference",
            "nodeId": "8597c53d-fc28-4ca0-ae9b-e24c375f4644",
            "location": {
              "start": {
                "offset": 0,
                "line": 1,
                "column": 1
              },
              "end": {
                "offset": 0,
                "line": 1,
                "column": 1
              }
            },
            "valueType": "varIdentifier",
            "isVariableReference": true,
            "identifier": "greeting"
          }
        ]
      },
      "raw": {
        "variable": "@greeting"
      },
      "meta": {}
    },
    {
      "type": "Directive",
      "nodeId": "1f700782-4294-4a40-b62b-138a051df5ff",
      "location": {
        "start": {
          "offset": 0,
          "line": 1,
          "column": 1
        },
        "end": {
          "offset": 11,
          "line": 1,
          "column": 12
        }
      },
      "kind": "add",
      "subtype": "addVariable",
      "source": "variable",
      "values": {
        "variable": [
          {
            "type": "VariableReference",
            "nodeId": "7b00488d-8eab-4a31-b4ed-3f6e81c0b765",
            "location": {
              "start": {
                "offset": 0,
                "line": 1,
                "column": 1
              },
              "end": {
                "offset": 0,
                "line": 1,
                "column": 1
              }
            },
            "valueType": "varIdentifier",
            "isVariableReference": true,
            "identifier": "count"
          }
        ]
      },
      "raw": {
        "variable": "@count"
      },
      "meta": {}
    }
  ],
  "metadata": {
    "kind": "import",
    "subtype": "selected"
  }
}