{
  "name": "run-exec",
  "input": "@run @greetCommand",
  "expected": "Hello from predefined command",
  "directives": [
    "@run @greetCommand"
  ],
  "ast": [
    {
      "type": "Directive",
      "nodeId": "66059624-c18c-4e60-ab60-769acf413993",
      "location": {
        "start": {
          "offset": 0,
          "line": 1,
          "column": 1
        },
        "end": {
          "offset": 18,
          "line": 1,
          "column": 19
        }
      },
      "kind": "run",
      "subtype": "runExec",
      "source": "exec",
      "values": {
        "identifier": [
          {
            "type": "Text",
            "nodeId": "867e2927-1e72-42bc-b3ba-17bb37ca5180",
            "location": {
              "start": {
                "offset": 6,
                "line": 1,
                "column": 7
              },
              "end": {
                "offset": 18,
                "line": 1,
                "column": 19
              }
            },
            "content": "greetCommand"
          }
        ],
        "args": []
      },
      "raw": {
        "identifier": "greetCommand",
        "args": []
      },
      "meta": {
        "argumentCount": 0
      }
    }
  ],
  "metadata": {
    "kind": "run",
    "subtype": "exec"
  }
}